conf/__init__.py
conf/config.py
models/__init__.py
models/es_model.py
models/faiss_model.py
models/graph_user_model.py
models/_base/__init__.py
models/_base/model.py
project_utils/__init__.py
project_utils/components/__init__.py
project_utils/components/elasticsearch/__init__.py
project_utils/components/elasticsearch/_base.py
project_utils/components/elasticsearch/_connection/__init__.py
project_utils/components/elasticsearch/_connection/_connection.py
project_utils/components/elasticsearch/_context/__init__.py
project_utils/components/elasticsearch/_context/_async_context.py
project_utils/components/elasticsearch/_context/_base.py
project_utils/components/elasticsearch/_context/_context.py
project_utils/components/elasticsearch/_context/_utils.py
project_utils/components/elasticsearch/_operation/__init__.py
project_utils/components/elasticsearch/_operation/_async_operation.py
project_utils/components/elasticsearch/_operation/_base.py
project_utils/components/elasticsearch/_operation/_operation.py
project_utils/components/elasticsearch/_operation/_utils.py
project_utils/components/elasticsearch/_session/__init__.py
project_utils/components/elasticsearch/_session/_session.py
project_utils/components/faiss/__init__.py
project_utils/components/faiss/_base.py
project_utils/components/faiss/_app/__init__.py
project_utils/components/faiss/_app/_app.py
project_utils/components/faiss/_app/_base.py
project_utils/components/faiss/_index/__init__.py
project_utils/components/faiss/_index/_base.py
project_utils/components/faiss/_index/_index.py
project_utils/components/faiss/_store/__init__.py
project_utils/components/faiss/_store/_base.py
project_utils/components/faiss/_store/_store.py
project_utils/components/ftp/__init__.py
project_utils/components/ftp/_ftp.py
project_utils/components/graph/__init__.py
project_utils/components/graph/_base.py
project_utils/components/graph/_connect/__init__.py
project_utils/components/graph/_connect/_base.py
project_utils_config-2.0.0.dist-info/METADATA
project_utils_config-2.0.0.dist-info/WHEEL
project_utils_config-2.0.0.dist-info/top_level.txt
project_utils_config-2.0.0.dist-info/RECORD
