Metadata-Version: 2.1
Name: project-utils-config
Version: 2.0.0
Summary: python project utils,version from 2.0.0
Home-page: https://gitee.com/mylx2014/project-utils.git
Author: mylx2014
Author-email: mylx2014@163.com
License: MIT
Keywords: python,utils,project utils
Classifier: Programming Language :: Python :: 3.8
Requires-Dist: asyncio
Requires-Dist: loguru
